gpg_exchange/__init__.py
gpg_exchange/exchange.py
gpg_exchange-0.0.7.dist-info/METADATA
gpg_exchange-0.0.7.dist-info/RECORD
gpg_exchange-0.0.7.dist-info/WHEEL
gpg_exchange-0.0.7.dist-info/top_level.txt
