Metadata-Version: 2.1
Name: gpg-exchange
Version: 0.0.7
Summary: Simplified GPG exchange
Home-page: https://github.com/lhelwerd/gpg-exchange
Author: Leon Helwerda
Author-email: l.s.helwerda@liacs.leidenuniv.nl
License: GPL3+
Keywords: gpg,exchange
Platform: UNKNOWN
Classifier: Development Status :: 3 - Alpha
Classifier: Intended Audience :: Developers
Classifier: License :: OSI Approved :: GNU General Public License v3 or later (GPLv3+)
Classifier: Operating System :: Microsoft :: Windows
Classifier: Operating System :: POSIX
Classifier: Programming Language :: Python
Classifier: Programming Language :: Python :: 2.7
Classifier: Programming Language :: Python :: 3.6
Classifier: Topic :: Security :: Cryptography
Requires-Dist: gpg
